rpy2_arrow/__init__.py
rpy2_arrow/arrow.py
rpy2_arrow/polars.py
rpy2_arrow/pyarrow_rarrow.py
rpy2_arrow/r6b.py
rpy2_arrow/tests.py
rpy2_arrow/tests_polars.py
rpy2_arrow/tests_r6b.py
rpy2_arrow-0.1.3.dist-info/licenses/LICENSE
rpy2_arrow-0.1.3.dist-info/METADATA
rpy2_arrow-0.1.3.dist-info/WHEEL
rpy2_arrow-0.1.3.dist-info/top_level.txt
rpy2_arrow-0.1.3.dist-info/RECORD
